sciberia/__init__.py
sciberia/process.py
sciberia/reader.py
sciberia-0.1.6.dist-info/LICENSE
sciberia-0.1.6.dist-info/METADATA
sciberia-0.1.6.dist-info/WHEEL
sciberia-0.1.6.dist-info/top_level.txt
sciberia-0.1.6.dist-info/RECORD
