Metadata-Version: 2.1
Name: sciberia
Version: 0.1.6
Summary: Sciberia helper libraries
Home-page: https://github.com/sciberia-llc/sciberia
Author: Sciberia, LLC
Author-email: info@sciberia.io
License: MIT
Platform: UNKNOWN
Classifier: License :: OSI Approved :: MIT License
Classifier: Programming Language :: Python :: 3
Classifier: Programming Language :: Python :: 3.7
License-File: LICENSE
Requires-Dist: numpy
Requires-Dist: pydicom
Requires-Dist: pynrrd
Requires-Dist: pytest
Requires-Dist: scipy
